wdb.server-3.1.0.data/scripts/wdb.server.py
wdb.server-3.1.0.dist-info/DESCRIPTION.rst
wdb.server-3.1.0.dist-info/METADATA
wdb.server-3.1.0.dist-info/RECORD
wdb.server-3.1.0.dist-info/WHEEL
wdb.server-3.1.0.dist-info/metadata.json
wdb.server-3.1.0.dist-info/top_level.txt
wdb_server/__init__.py
wdb_server/state.py
wdb_server/streams.py
wdb_server/utils.py
wdb_server/static/img/bg-left.png
wdb_server/static/img/bg-right.png
wdb_server/static/javascripts/wdb/deps.min.js
wdb_server/static/javascripts/wdb/home.min.js
wdb_server/static/javascripts/wdb/wdb.min.js
wdb_server/static/libs/material-design-lite/material.indigo-red.min.css
wdb_server/static/libs/material-design-lite/material.min.js
wdb_server/static/libs/material-design-lite/material.red-indigo.min.css
wdb_server/static/libs/material-design-lite/material.teal-orange.min.css
wdb_server/static/stylesheets/deps.min.css
wdb_server/static/stylesheets/home.css
wdb_server/static/stylesheets/wdb.css
wdb_server/templates/_layout.html
wdb_server/templates/home.html
wdb_server/templates/wdb.html
